phpgoody/__init__.py
phpgoody-1.0.9.dist-info/LICENSE
phpgoody-1.0.9.dist-info/METADATA
phpgoody-1.0.9.dist-info/WHEEL
phpgoody-1.0.9.dist-info/top_level.txt
phpgoody-1.0.9.dist-info/RECORD
