Metadata-Version: 2.1
Name: phpgoody
Version: 1.0.9
Summary: Some useful php functions implemented by python.
Home-page: https://blog.gwlin.com
Author: Elevioux
Author-email: elevioux@live.com
License: MIT License
Platform: all
Requires-Python: >=3.11
License-File: LICENSE
Requires-Dist: dateutils>=0.6
